[
  {
    "id": "5b93f6ee6f5ba74b3bcda748",
    "activation": "2018-09-08T16:25:17.074Z",
    "expiry": "2018-09-08T17:23:01.680Z",
    "mission": {
      "node": "Minthe (Pluto)",
      "type": "Mobile Defense",
      "faction": "Corpus",
      "reward": {
        "items": [],
        "countedItems": [],
        "credits": 12500,
        "asString": "12500cr",
        "itemString": "",
        "thumbnail": "https://i.imgur.com/JCKyUXJ.png",
        "color": 15844367
      },
      "minEnemyLevel": 34,
      "maxEnemyLevel": 38,
      "nightmare": false,
      "archwingRequired": false
    },
    "expired": false,
    "eta": "24m 39s",
    "rewardTypes": ["credits"]
  },
  {
    "id": "5b93faaeba7fdbb648f94cba",
    "activation": "2018-09-08T16:41:21.785Z",
    "expiry": "2018-09-08T17:43:24.308Z",
    "mission": {
      "node": "Tiwaz (Void)",
      "type": "Extermination",
      "faction": "Orokin",
      "reward": {
        "items": [],
        "countedItems": [{ "count": 20, "type": "Void Traces" }],
        "credits": 10100,
        "asString": "20 Void Traces + 10100cr",
        "itemString": "20 Void Traces",
        "thumbnail": "https://i.imgur.com/vvZGMPv.png",
        "color": 6923485
      },
      "minEnemyLevel": 24,
      "maxEnemyLevel": 29,
      "nightmare": false,
      "archwingRequired": false
    },
    "expired": false,
    "eta": "45m 2s",
    "rewardTypes": ["traces"]
  },
  {
    "id": "5b93fe6d7b6fa3aa4fe97b99",
    "activation": "2018-09-08T16:57:12.716Z",
    "expiry": "2018-09-08T17:54:48.109Z",
    "mission": {
      "node": "Shklovsky (Phobos)",
      "type": "Extermination",
      "faction": "Corpus",
      "reward": {
        "items": ["Accelerated Blast"],
        "countedItems": [],
        "credits": 6500,
        "asString": "Accelerated Blast + 6500cr",
        "itemString": "Accelerated Blast",
        "thumbnail": "https://i.imgur.com/cAYNH7j.png",
        "color": 11677228
      },
      "minEnemyLevel": 15,
      "maxEnemyLevel": 17,
      "nightmare": true,
      "archwingRequired": false
    },
    "expired": false,
    "eta": "56m 25s",
    "rewardTypes": ["nightmare"]
  }
]
